amey_ml/__init__.py
amey_ml/decision_tree.py
amey_ml/k_means.py
amey_ml/knn_classify.py
amey_ml/linear_regression.py
amey_ml/naive_bayes.py
amey_ml/nn_keras.py
amey_ml-0.1.10.dist-info/METADATA
amey_ml-0.1.10.dist-info/WHEEL
amey_ml-0.1.10.dist-info/top_level.txt
amey_ml-0.1.10.dist-info/RECORD
