Metadata-Version: 2.1
Name: amey-ml
Version: 0.1.10
Summary: A Machine Learning Library for the noobies
Author: Amey Shinde
Author-email: <amey.shinde@bizzencecollab.com>
Keywords: python,machinelearning
Requires-Dist: numpy
Requires-Dist: tensorflow
Requires-Dist: pandas
Requires-Dist: scikit-learn
Requires-Dist: keras
